[
    {
        "display_name": "AI Image",
        "id": "ai_image",
        "class": "AIImage"
    },
    {
        "display_name": "AI Text",
        "id": "ai_text",
        "class": "AIText"
    },
    {
        "display_name": "Image Upload",
        "id": "image_upload",
        "class": "ImageUpload"
    },
    {
        "display_name": "Today's Newspaper",
        "id": "newspaper",
        "class": "Newspaper",
        "image_settings": ["keep-width"]
    },
    {
        "display_name": "Clock",
        "id": "clock",
        "class": "Clock"
    },
    {
        "display_name": "Weather",
        "id": "weather",
        "class": "Weather"
    }
]